[
    {
        "start": 0.109,
        "end": 27.498,
        "text": " morning i warned you yesterday that the department of homeland security under biden and mayorkas two absolutely corrupt individuals are now putting out a warning oh man election day could be trouble could be some uh interference with hackers and stuff like that unbelievably i'm putting the show together this morning remnants of it i put the core of it together last night and i sent this over to jim jim did you not get it this morning yes he did",
        "speaker": "SPEAKER_06"
    },
    {
        "start": 29.09,
        "end": 32.172,
        "text": " Hackers to back Kamala Harris at Vegas fundraiser.",
        "speaker": "SPEAKER_06"
    },
    {
        "start": 32.593,
        "end": 33.693,
        "text": "Axios, Sam Sabin.",
        "speaker": "SPEAKER_06"
    },
    {
        "start": 35.034,
        "end": 44.761,
        "text": "They note that this guy, who's a co-founder of DEFCON Voting Village, says he was motivated to host this event after Kamala Harris supported the election security community in 2018.",
        "speaker": "SPEAKER_06"
    },
    {
        "start": 44.861,
        "end": 46.202,
        "text": "Wait, it gets better.",
        "speaker": "SPEAKER_06"
    },
    {
        "start": 46.743,
        "end": 54.909,
        "text": "At the time, lobbyists for voting machine vendors were attacking the village for its plans to test voting machines for security flaws.",
        "speaker": "SPEAKER_06"
    },
    {
        "start": 54.929,
        "end": 55.589,
        "text": "That's it.",
        "speaker": "SPEAKER_06"
    },
    {
        "start": 66.392,
        "end": 72.618,
        "text": " I, you know, I would never dare compare myself to patriots like Paul Revere, like and others.",
        "speaker": "SPEAKER_06"
    },
    {
        "start": 72.678,
        "end": 72.858,
        "text": "Right.",
        "speaker": "SPEAKER_06"
    },
    {
        "start": 73.038,
        "end": 74.8,
        "text": "That would be disgraceful and disgusting.",
        "speaker": "SPEAKER_06"
    },
    {
        "start": 75.74,
        "end": 84.208,
        "text": "But I feel like I'm kind of like the guy, you know, like when you ever go see a TV show live and noise is a guy who holds up a cue card.",
        "speaker": "SPEAKER_06"
    },
    {
        "start": 84.568,
        "end": 89.212,
        "text": "I feel like I'm the guy like with the cue card up, like they're telling you what's going to happen.",
        "speaker": "SPEAKER_06"
    },
    {
        "start": 89.533,
        "end": 90.333,
        "text": "Applaud now.",
        "speaker": "SPEAKER_06"
    },
    {
        "start": 90.894,
        "end": 91.855,
        "text": "Like they're telling you.",
        "speaker": "SPEAKER_06"
    },
    {
        "start": 94.364,
        "end": 102.526,
        "text": " What other signal could you possibly need that they are planning some electronic attack on Election Day?",
        "speaker": "SPEAKER_06"
    },
    {
        "start": 103.666,
        "end": 111.147,
        "text": "There is not a single substantial substantive, excuse me, reason for you to wait and not bank your vote early.",
        "speaker": "SPEAKER_06"
    },
    {
        "start": 111.167,
        "end": 112.808,
        "text": "When I say bank your vote, I mean vote early.",
        "speaker": "SPEAKER_06"
    },
    {
        "start": 113.808,
        "end": 114.488,
        "text": "There's not one.",
        "speaker": "SPEAKER_06"
    },
    {
        "start": 116.048,
        "end": 116.829,
        "text": "More on this coming up.",
        "speaker": "SPEAKER_06"
    },
    {
        "start": 120.749,
        "end": 125.471,
        "text": " Rock-On, Harley-Davidson, and Rock-On Power Sports, West Henrietta Road.",
        "speaker": "SPEAKER_15"
    },
    {
        "start": 125.791,
        "end": 131.113,
        "text": "Shop the greatest selection of legendary Harleys and save big on a wide array of used bikes.",
        "speaker": "SPEAKER_15"
    },
    {
        "start": 131.533,
        "end": 135.455,
        "text": "And Rock-On Power Sports has rides from Honda, Kawasaki, and Yamaha.",
        "speaker": "SPEAKER_15"
    },
    {
        "start": 136.055,
        "end": 139.316,
        "text": "Rock-On has a helpful staff to save you big money.",
        "speaker": "SPEAKER_15"
    },
    {
        "start": 139.856,
        "end": 146.199,
        "text": "The Rock-On service department has expert technicians and a great supply of parts to get and keep you on two wheels.",
        "speaker": "SPEAKER_15"
    },
    {
        "start": 147.499,
        "end": 152.101,
        "text": " WYSL listeners get $500 off used motorcycles while supplies last.",
        "speaker": "SPEAKER_15"
    },
    {
        "start": 152.721,
        "end": 156.262,
        "text": "Rock-On has side-by-sides, ATVs and jet boats too.",
        "speaker": "SPEAKER_15"
    },
    {
        "start": 156.882,
        "end": 159.163,
        "text": "Anything that's fun and goes fast.",
        "speaker": "SPEAKER_15"
    },
    {
        "start": 159.803,
        "end": 163.945,
        "text": "On and off road and on the water, shop the all-new Rock-On first.",
        "speaker": "SPEAKER_15"
    },
    {
        "start": 164.825,
        "end": 169.912,
        "text": " Rock on Harley-Davidson and Rock on Motorsports, 2600 West Henrietta Road.",
        "speaker": "SPEAKER_15"
    },
    {
        "start": 170.553,
        "end": 171.835,
        "text": "Open Tuesday through Saturday.",
        "speaker": "SPEAKER_15"
    },
    {
        "start": 172.116,
        "end": 172.396,
        "text": "Call 424-2120.",
        "speaker": "SPEAKER_15"
    },
    {
        "start": 172.436,
        "end": 173.578,
        "text": "Visit rockonharleydavidson.com.",
        "speaker": "SPEAKER_15"
    },
    {
        "start": 177.975,
        "end": 183.596,
        "text": " Today's heat pump systems are a better, more convenient way to keep your home comfortable all year round.",
        "speaker": "SPEAKER_19"
    },
    {
        "start": 183.996,
        "end": 188.857,
        "text": "They'll keep you cool on the hottest summer days and keep you warm on the coldest winter nights.",
        "speaker": "SPEAKER_19"
    },
    {
        "start": 189.357,
        "end": 196.199,
        "text": "Plus, these all-weather ductless or ducted systems are up to 40% more efficient than conventional heating and cooling systems.",
        "speaker": "SPEAKER_19"
    },
    {
        "start": 196.759,
        "end": 201.52,
        "text": "Upgrade to an energy-efficient heat pump system and take advantage of clean heat rebates.",
        "speaker": "SPEAKER_19"
    },
    {
        "start": 201.92,
        "end": 203.82,
        "text": "Find out more at airquipheating.com.",
        "speaker": "SPEAKER_19"
    },
    {
        "start": 208.067,
        "end": 212.57,
        "text": " Hi, my name is Greg Sadwick, and along with my son, Zach, we are the owners of Flower City Collision.",
        "speaker": "SPEAKER_23"
    },
    {
        "start": 212.83,
        "end": 217.073,
        "text": "We've been advertisers on WISL, the voice of liberty, for the last couple of years.",
        "speaker": "SPEAKER_23"
    },
    {
        "start": 217.373,
        "end": 227.8,
        "text": "So I want to thank the listeners of WISL for their patronage, which has allowed us to grow and reinvest in the latest technologies to ensure that your vehicles are repaired to the most current standards, whether conventional or EV.",
        "speaker": "SPEAKER_23"
    },
    {
        "start": 228.06,
        "end": 237.567,
        "text": "If you're in a collision, reach out to Zach at Flower City Collision in Henrietta, and he'll work with your national insurance company on your local behalf to ensure that your repair gets done right.",
        "speaker": "SPEAKER_23"
    },
    {
        "start": 238.187,
        "end": 239.128,
        "text": " 27,000 watts.",
        "speaker": "SPEAKER_08"
    },
    {
        "start": 239.448,
        "end": 240.149,
        "text": "W-Y-S-L.",
        "speaker": "SPEAKER_08"
    },
    {
        "start": 240.449,
        "end": 244.612,
        "text": "AM 1040, Avon, Rochester.",
        "speaker": "SPEAKER_08"
    },
    {
        "start": 244.632,
        "end": 246.133,
        "text": "FM 92.1, Rochester.",
        "speaker": "SPEAKER_08"
    },
    {
        "start": 246.754,
        "end": 247.754,
        "text": "FM 95.5, Spencerport.",
        "speaker": "SPEAKER_08"
    },
    {
        "start": 247.854,
        "end": 252.798,
        "text": "Breaking news this hour from townhall.com.",
        "speaker": "SPEAKER_10"
    },
    {
        "start": 253.038,
        "end": 253.799,
        "text": "I'm John Scott.",
        "speaker": "SPEAKER_10"
    },
    {
        "start": 255.48,
        "end": 256.02,
        "text": "Several U.S.",
        "speaker": "SPEAKER_10"
    },
    {
        "start": 256.04,
        "end": 260.504,
        "text": "personnel injured in a suspected rocket attack at a military base in Iraq.",
        "speaker": "SPEAKER_10"
    },
    {
        "start": 261.24,
        "end": 269.586,
        "text": " Florida Republican Congressman Mike Walz tells the Salem Radio Network this was just the latest in a series of unanswered attacks from Iran.",
        "speaker": "SPEAKER_10"
    },
    {
        "start": 269.706,
        "end": 280.874,
        "text": "And this was a return from Iran's proxies in Iraq attacking our bases, which they did hundreds of times in the run-up to October 7th.",
        "speaker": "SPEAKER_02"
    },
    {
        "start": 280.934,
        "end": 284.256,
        "text": "And you remember we had the three that were killed.",
        "speaker": "SPEAKER_02"
    },
    {
        "start": 284.537,
        "end": 289.16,
        "text": "And to this day, in the last three years, Iran has not paid a price.",
        "speaker": "SPEAKER_02"
    },
    {
        "start": 289.636,
        "end": 292.698,
        "text": " Troops at Al-Asad Air Base still assessing the injuries and damage.",
        "speaker": "SPEAKER_10"
    },
    {
        "start": 293.138,
        "end": 297.16,
        "text": "It appeared as many as seven military troops and civilians were injured.",
        "speaker": "SPEAKER_10"
    },
    {
        "start": 297.781,
        "end": 310.267,
        "text": "The attack comes as tensions across the Middle East are spiking, following the killings last week of a senior Hezbollah commander in Lebanon and Hamas' top political leader in Iran in suspected Israeli strikes.",
        "speaker": "SPEAKER_10"
    },
    {
        "start": 310.728,
        "end": 312.569,
        "text": "Both groups are backed by Iran.",
        "speaker": "SPEAKER_10"
    },
    {
        "start": 313.567,
        "end": 324.36,
        "text": " Also at townhall.com, National Weather Service meteorologist Scott Klebauer says most warnings related to Tropical Storm Debbie are centered around the Carolinas and Georgia.",
        "speaker": "SPEAKER_10"
    },
    {
        "start": 324.38,
        "end": 326.642,
        "text": "There are other areas being affected.",
        "speaker": "SPEAKER_10"
    },
    {
        "start": 326.682,
        "end": 332.069,
        "text": "There could also be a few severe thunderstorm warnings or maybe even tornado warnings.",
        "speaker": "SPEAKER_03"
    },
    {
        "start": 332.569,
        "end": 341.378,
        "text": " Across the northern plains, and the northern, excuse me, the northern and central plains, with two disturbances that are going to be moving through the area.",
        "speaker": "SPEAKER_03"
    },
    {
        "start": 341.458,
        "end": 345.462,
        "text": "So far, the storm has brought heavy rain to Florida, Georgia, and north and south Carolina.",
        "speaker": "SPEAKER_10"
    },
    {
        "start": 346.143,
        "end": 351.108,
        "text": "This late update on the Park Fire, the fourth largest in California history, nearly 426,000 acres have burned.",
        "speaker": "SPEAKER_10"
    },
    {
        "start": 351.128,
        "end": 351.828,
        "text": "It's only 34% contained.",
        "speaker": "SPEAKER_10"
    },
    {
        "start": 357.498,
        "end": 359.659,
        "text": " On Wall Street, stocks finishing lower today.",
        "speaker": "SPEAKER_10"
    },
    {
        "start": 359.739,
        "end": 361.0,
        "text": "The Dow was down 234 points.",
        "speaker": "SPEAKER_10"
    },
    {
        "start": 361.02,
        "end": 361.58,
        "text": "The Nasdaq losing 171.",
        "speaker": "SPEAKER_10"
    },
    {
        "start": 361.62,
        "end": 363.441,
        "text": "More at townhall.com.",
        "speaker": "SPEAKER_10"
    },
    {
        "start": 368.624,
        "end": 371.366,
        "text": " For anyone with everyday aches and pains, I've got a question.",
        "speaker": "SPEAKER_11"
    },
    {
        "start": 371.787,
        "end": 372.928,
        "text": "What are you missing out on?",
        "speaker": "SPEAKER_11"
    },
    {
        "start": 373.288,
        "end": 374.169,
        "text": "Probably a lot.",
        "speaker": "SPEAKER_11"
    },
    {
        "start": 374.489,
        "end": 376.55,
        "text": "So let me tell you about Relief Factor.",
        "speaker": "SPEAKER_11"
    },
    {
        "start": 376.951,
        "end": 381.655,
        "text": "Relief Factor is a drug-free daily supplement that helps your body fight pain naturally.",
        "speaker": "SPEAKER_11"
    },
    {
        "start": 382.015,
        "end": 383.276,
        "text": "It doesn't just mask pain.",
        "speaker": "SPEAKER_11"
    },
    {
        "start": 383.556,
        "end": 385.718,
        "text": "It helps reduce or even eliminate it.",
        "speaker": "SPEAKER_11"
    },
    {
        "start": 386.098,
        "end": 389.501,
        "text": "In about three weeks, you'll discover what it's like to feel better.",
        "speaker": "SPEAKER_11"
    },
    {
        "start": 389.781,
        "end": 395.143,
        "text": " Go to reliefactor.com or call 1-800-4-RELIEF and save on your first order.",
        "speaker": "SPEAKER_11"
    },
    {
        "start": 395.543,
        "end": 398.384,
        "text": "That's 1-800-4-RELIEF.",
        "speaker": "SPEAKER_11"
    },
    {
        "start": 398.464,
        "end": 400.905,
        "text": "My doctor told me my blood pressure is borderline.",
        "speaker": "SPEAKER_00"
    },
    {
        "start": 400.925,
        "end": 404.606,
        "text": "I figured I could worry about it or do something about it.",
        "speaker": "SPEAKER_00"
    },
    {
        "start": 404.966,
        "end": 408.167,
        "text": "So I took control with Garlic Healthy Pressure Formula.",
        "speaker": "SPEAKER_00"
    },
    {
        "start": 408.527,
        "end": 414.792,
        "text": " It works safely and naturally to help maintain healthy blood pressure with a custom blend of garlic, vitamins, and minerals.",
        "speaker": "SPEAKER_00"
    },
    {
        "start": 415.352,
        "end": 416.493,
        "text": "And it's odor-free.",
        "speaker": "SPEAKER_00"
    },
    {
        "start": 416.513,
        "end": 420.356,
        "text": "I'm taking charge with Garlic Healthy Blood Pressure Formula.",
        "speaker": "SPEAKER_00"
    },
    {
        "start": 420.776,
        "end": 422.717,
        "text": "These statements have not been evaluated by the FDA.",
        "speaker": "SPEAKER_25"
    },
    {
        "start": 422.757,
        "end": 425.88,
        "text": "This product is not intended to diagnose, treat, cure, or prevent any disease.",
        "speaker": "SPEAKER_25"
    },
    {
        "start": 426.576,
        "end": 430.678,
        "text": " Here's the latest forecast from the News 10 NBC Weather Center.",
        "speaker": "SPEAKER_05"
    },
    {
        "start": 430.798,
        "end": 433.039,
        "text": "For tonight, clear and comfortably cool.",
        "speaker": "SPEAKER_05"
    },
    {
        "start": 433.399,
        "end": 435.6,
        "text": "We'll dip down into the 50s on Thursday.",
        "speaker": "SPEAKER_05"
    },
    {
        "start": 435.64,
        "end": 436.88,
        "text": "Some increasing clouds.",
        "speaker": "SPEAKER_05"
    },
    {
        "start": 436.92,
        "end": 442.523,
        "text": "Just a small chance of a late-day shower, but most of the day dry into the upper 70s.",
        "speaker": "SPEAKER_05"
    },
    {
        "start": 442.563,
        "end": 444.643,
        "text": "Now, we've got to keep an eye out for Friday.",
        "speaker": "SPEAKER_05"
    },
    {
        "start": 445.124,
        "end": 453.407,
        "text": "The remnants of Debbie will move in with some locally heavy rain and the chance for some localized flooding to end the week.",
        "speaker": "SPEAKER_05"
    },
    {
        "start": 453.427,
        "end": 454.487,
        "text": "I'm Rich Coniglia, WYSL.",
        "speaker": "SPEAKER_05"
    },
    {
        "start": 456.081,
        "end": 459.144,
        "text": " The following is brought to you by the Allegheny County Scope.",
        "speaker": "SPEAKER_04"
    },
    {
        "start": 459.364,
        "end": 461.646,
        "text": "This is Attorney Paloma Capanna.",
        "speaker": "SPEAKER_01"
    },
    {
        "start": 462.006,
        "end": 471.654,
        "text": "If you carry concealed, get ready for further proceedings in federal court in Manhattan about prohibitions against carry in sensitive and restricted areas.",
        "speaker": "SPEAKER_01"
    },
    {
        "start": 471.834,
        "end": 480.622,
        "text": "The prohibitions are part of the 2022 Concealed Carry Improvements Act and are challenged as being unconstitutional under the Second Amendment.",
        "speaker": "SPEAKER_01"
    },
    {
        "start": 480.97,
        "end": 484.592,
        "text": " Please consider joining Allegheny County Scope 716-913-8176.",
        "speaker": "SPEAKER_04"
    },
    {
        "start": 485.032,
        "end": 489.475,
        "text": "Hi, this is Emily.",
        "speaker": "SPEAKER_04"
    },
    {
        "start": 489.775,
        "end": 491.876,
        "text": "And Jim from Colby's Ice Cream and Bakery.",
        "speaker": "SPEAKER_20"
    },
    {
        "start": 492.076,
        "end": 494.277,
        "text": "Our fresh baked pie selection is bigger than ever.",
        "speaker": "SPEAKER_20"
    },
    {
        "start": 494.497,
        "end": 499.7,
        "text": "Our 36 flavors of hard ice cream and Upstate's best frozen custard are yum.",
        "speaker": "SPEAKER_22"
    },
    {
        "start": 499.98,
        "end": 503.582,
        "text": "I'm baking cookies, sweetbreads, and pastries that are extra tasty.",
        "speaker": "SPEAKER_20"
    },
    {
        "start": 503.722,
        "end": 506.444,
        "text": "Our hard ice cream milkshakes are to die for.",
        "speaker": "SPEAKER_20"
    },
    {
        "start": 506.764,
        "end": 509.306,
        "text": " Everyone loves our cannolis, brownies, and cream puffs.",
        "speaker": "SPEAKER_20"
    },
    {
        "start": 509.487,
        "end": 511.248,
        "text": "Can't beat our ice cream sundaes.",
        "speaker": "SPEAKER_20"
    },
    {
        "start": 511.489,
        "end": 513.37,
        "text": "Our homemade donuts are the best in town.",
        "speaker": "SPEAKER_20"
    },
    {
        "start": 513.53,
        "end": 515.272,
        "text": "Colby's Ice Cream and Bake Shop.",
        "speaker": "SPEAKER_15"
    },
    {
        "start": 515.492,
        "end": 517.955,
        "text": "Open I-390, exit 11 in Rush.",
        "speaker": "SPEAKER_07"
    },
    {
        "start": 518.795,
        "end": 520.537,
        "text": "Open Door Mission is deeply grateful.",
        "speaker": "SPEAKER_07"
    },
    {
        "start": 521.058,
        "end": 523.36,
        "text": "Because of your generous hearts, you've opened many doors.",
        "speaker": "SPEAKER_07"
    },
    {
        "start": 524.0,
        "end": 527.063,
        "text": "For those in need to find shelter with respect and dignity.",
        "speaker": "SPEAKER_07"
    },
    {
        "start": 527.944,
        "end": 530.706,
        "text": " For families who are revitalized with hope and strength.",
        "speaker": "SPEAKER_07"
    },
    {
        "start": 531.626,
        "end": 536.009,
        "text": "For restored healthy relationships for those on the road to lifelong recovery.",
        "speaker": "SPEAKER_07"
    },
    {
        "start": 536.889,
        "end": 539.471,
        "text": "For people empowered with new skills and opportunities.",
        "speaker": "SPEAKER_07"
    },
    {
        "start": 540.631,
        "end": 543.133,
        "text": "With your continued help, more doors will open.",
        "speaker": "SPEAKER_07"
    },
    {
        "start": 552.97,
        "end": 557.434,
        "text": " Patchwork Saddlery in Avon is an independent fitter working with many brands.",
        "speaker": "SPEAKER_21"
    },
    {
        "start": 557.594,
        "end": 562.819,
        "text": "Our qualified saddle fitter through the Society of Master Saddlers can fit and measure your horse.",
        "speaker": "SPEAKER_21"
    },
    {
        "start": 563.02,
        "end": 567.163,
        "text": "Patchwork Saddlery can check your saddle regularly as preventative maintenance.",
        "speaker": "SPEAKER_21"
    },
    {
        "start": 567.384,
        "end": 571.448,
        "text": "Visit our showroom, East Main Street, Avon, next to Tompkins Community Bank.",
        "speaker": "SPEAKER_21"
    },
    {
        "start": 571.548,
        "end": 573.369,
        "text": "Put your money where your heart is.",
        "speaker": "SPEAKER_21"
    },
    {
        "start": 573.73,
        "end": 575.832,
        "text": "Shop locally at Patchwork Saddlery.",
        "speaker": "SPEAKER_21"
    },
    {
        "start": 578.638,
        "end": 580.722,
        "text": " Are you in need of a top-notch general surgeon?",
        "speaker": "SPEAKER_12"
    },
    {
        "start": 581.063,
        "end": 585.471,
        "text": "Look no farther than UR Medicine Noise Health, your trusted healthcare partner.",
        "speaker": "SPEAKER_12"
    },
    {
        "start": 586.576,
        "end": 592.478,
        "text": " At Noise Health, we prioritize your well-being, offering state-of-the-art facilities at two convenient locations.",
        "speaker": "SPEAKER_12"
    },
    {
        "start": 593.178,
        "end": 596.24,
        "text": "Our team of highly skilled surgeons is dedicated to your care.",
        "speaker": "SPEAKER_12"
    },
    {
        "start": 596.88,
        "end": 601.622,
        "text": "Choose UR Medicine Noise Health for a surgical experience that goes beyond expectations.",
        "speaker": "SPEAKER_12"
    },
    {
        "start": 602.162,
        "end": 603.942,
        "text": "Call 585-335-7179 to schedule your consultation today.",
        "speaker": "SPEAKER_12"
    },
    {
        "start": 604.003,
        "end": 604.343,
        "text": "W-I-S-L",
        "speaker": "SPEAKER_12"
    },
    {
        "start": 624.955,
        "end": 636.707,
        "text": " From the NYPD to the Secret Service to behind the microphone, taking the fight to the radical left and the putrid swamp, you're listening to The Dan Bongino Show.",
        "speaker": "SPEAKER_13"
    },
    {
        "start": 638.629,
        "end": 641.051,
        "text": "Here he is, Dan Bongino.",
        "speaker": "SPEAKER_13"
    },
    {
        "start": 642.27,
        "end": 652.494,
        "text": " This is some of the most important segments we do because they directly impact your wallet that Kamala Harris wants to unburden with money.",
        "speaker": "SPEAKER_06"
    },
    {
        "start": 653.254,
        "end": 662.258,
        "text": "She wants to unburden it by lightening your wallet, removing some of that money and then placing it into government coffers so they can flush it down the toilet bowl.",
        "speaker": "SPEAKER_06"
    },
    {
        "start": 663.311,
        "end": 669.921,
        "text": " Here to talk about the current state of the economy is one of the best economic minds out there, a guy I follow on social media, and you should too.",
        "speaker": "SPEAKER_06"
    },
    {
        "start": 670.421,
        "end": 670.762,
        "text": "E.J.",
        "speaker": "SPEAKER_06"
    },
    {
        "start": 670.842,
        "end": 671.303,
        "text": "and Tony.",
        "speaker": "SPEAKER_06"
    },
    {
        "start": 671.323,
        "end": 672.605,
        "text": "E.J., welcome back to the show.",
        "speaker": "SPEAKER_06"
    },
    {
        "start": 673.766,
        "end": 675.148,
        "text": "Dan, thank you for having me again.",
        "speaker": "SPEAKER_18"
    },
    {
        "start": 676.061,
        "end": 681.305,
        "text": " Well, again, I follow you on social media because you're always ahead of the curve on these things.",
        "speaker": "SPEAKER_06"
    },
    {
        "start": 681.485,
        "end": 683.647,
        "text": "First, let me just ask you a very simple question.",
        "speaker": "SPEAKER_06"
    },
    {
        "start": 684.408,
        "end": 684.888,
        "text": "I get it.",
        "speaker": "SPEAKER_06"
    },
    {
        "start": 685.028,
        "end": 686.429,
        "text": "You know, one can predict the future.",
        "speaker": "SPEAKER_06"
    },
    {
        "start": 686.469,
        "end": 688.271,
        "text": "A thousand different variables could happen.",
        "speaker": "SPEAKER_06"
    },
    {
        "start": 688.331,
        "end": 688.711,
        "text": "Wars.",
        "speaker": "SPEAKER_06"
    },
    {
        "start": 689.051,
        "end": 689.452,
        "text": "I get it.",
        "speaker": "SPEAKER_06"
    },
    {
        "start": 689.512,
        "end": 694.836,
        "text": "But say we're on the current trajectory we're on now, the unemployment numbers, productivity numbers.",
        "speaker": "SPEAKER_06"
    },
    {
        "start": 695.477,
        "end": 699.66,
        "text": "Do you sense a recession might be close or even before the November election?",
        "speaker": "SPEAKER_06"
    },
    {
        "start": 699.68,
        "end": 700.801,
        "text": "Because that would change everything.",
        "speaker": "SPEAKER_06"
    },
    {
        "start": 702.153,
        "end": 703.514,
        "text": " Yeah, I really do, Dan.",
        "speaker": "SPEAKER_18"
    },
    {
        "start": 703.554,
        "end": 709.256,
        "text": "I would not be surprised, actually, if they eventually backdate a recession to beginning this month in August.",
        "speaker": "SPEAKER_18"
    },
    {
        "start": 709.676,
        "end": 721.962,
        "text": "And unfortunately, we're never going to know before the election whether one has actually begun or not, because we're not going to get that official pronouncement handed down to us, if you will.",
        "speaker": "SPEAKER_18"
    },
    {
        "start": 722.182,
        "end": 729.345,
        "text": "But I think the American people at this point can look around and see their own personal finances, see what's going on around them,",
        "speaker": "SPEAKER_18"
    },
    {
        "start": 729.646,
        "end": 732.747,
        "text": " and get a pretty good sense that the economy is not doing well",
        "speaker": "SPEAKER_18"
    },
    {
        "start": 733.763,
        "end": 735.184,
        "text": " Yeah, we're talking to E.J.",
        "speaker": "SPEAKER_06"
    },
    {
        "start": 735.224,
        "end": 735.724,
        "text": "and Tony.",
        "speaker": "SPEAKER_06"
    },
    {
        "start": 735.865,
        "end": 745.912,
        "text": "E.J., you know, what I don't like is the Democrats trying to distance themselves from policies that have been directly implicated in this economic malaise being caused right now.",
        "speaker": "SPEAKER_06"
    },
    {
        "start": 745.932,
        "end": 747.273,
        "text": "And I use that word intentionally.",
        "speaker": "SPEAKER_06"
    },
    {
        "start": 748.334,
        "end": 750.015,
        "text": "I am not naive.",
        "speaker": "SPEAKER_06"
    },
    {
        "start": 750.256,
        "end": 754.539,
        "text": "I understand that swampy Republicans for years have played into the debt crisis.",
        "speaker": "SPEAKER_06"
    },
    {
        "start": 754.999,
        "end": 761.804,
        "text": "And some of them are now playing into the current tax crisis as well with a lot of this manipulation, a lot of these manipulations of the tax code.",
        "speaker": "SPEAKER_06"
    },
    {
        "start": 761.844,
        "end": 762.245,
        "text": "I get it.",
        "speaker": "SPEAKER_06"
    },
    {
        "start": 762.885,
        "end": 765.168,
        "text": " And I just think the Democrats are far worse.",
        "speaker": "SPEAKER_06"
    },
    {
        "start": 765.408,
        "end": 768.332,
        "text": "And that's why, you know, I'm forced to vote Republican most of the time.",
        "speaker": "SPEAKER_06"
    },
    {
        "start": 768.372,
        "end": 769.894,
        "text": "I wish I could vote conservative.",
        "speaker": "SPEAKER_06"
    },
    {
        "start": 770.394,
        "end": 781.808,
        "text": "But there is absolutely zero doubt that team Biden, Harris, now Tim Walz are all on the side of borderline socialist, if not outright socialist type redistribution.",
        "speaker": "SPEAKER_06"
    },
    {
        "start": 782.308,
        "end": 784.891,
        "text": " They want a massive increase in the corporate tax rate.",
        "speaker": "SPEAKER_06"
    },
    {
        "start": 785.271,
        "end": 789.375,
        "text": "They want massive government spending to not only continue to be, but be enhanced.",
        "speaker": "SPEAKER_06"
    },
    {
        "start": 789.716,
        "end": 799.806,
        "text": "I mean, these are the types of things that are directly causing the economic crisis we're in now through things like crowd out and productivity problems as companies have to forfeit more money over to the government.",
        "speaker": "SPEAKER_06"
    },
    {
        "start": 801.674,
        "end": 802.755,
        "text": " Well, absolutely, Dan.",
        "speaker": "SPEAKER_18"
    },
    {
        "start": 802.795,
        "end": 804.396,
        "text": "That's all 100% right.",
        "speaker": "SPEAKER_18"
    },
    {
        "start": 804.436,
        "end": 805.457,
        "text": "I think you're spot on.",
        "speaker": "SPEAKER_18"
    },
    {
        "start": 805.577,
        "end": 812.823,
        "text": "And I would add to that that Kamala's VP pick even wants to put a surcharge tax on capital gains and dividends.",
        "speaker": "SPEAKER_18"
    },
    {
        "start": 812.843,
        "end": 816.326,
        "text": "Can you imagine what that's going to do to people's retirement accounts?",
        "speaker": "SPEAKER_18"
    },
    {
        "start": 816.586,
        "end": 825.093,
        "text": "I mean, it's just absolutely going to wipe them out because those taxes apply not just to real increases in value, but just nominal increases.",
        "speaker": "SPEAKER_18"
    },
    {
        "start": 825.133,
        "end": 828.876,
        "text": "In other words, as stocks go up because of inflation, which, by the way,",
        "speaker": "SPEAKER_18"
    },
    {
        "start": 829.216,
        "end": 833.878,
        "text": " accounts for three quarters of all the stock gains we have seen under the Biden-Harris administration.",
        "speaker": "SPEAKER_18"
    },
    {
        "start": 834.218,
        "end": 836.679,
        "text": "You don't just owe tax on the real increase.",
        "speaker": "SPEAKER_18"
    },
    {
        "start": 836.959,
        "end": 840.481,
        "text": "You even owe tax on the nominal increase from inflation.",
        "speaker": "SPEAKER_18"
    },
    {
        "start": 840.781,
        "end": 848.304,
        "text": "In other words, you add in these additional surcharges on top of that, and you end up with a negative real rate of return.",
        "speaker": "SPEAKER_18"
    },
    {
        "start": 848.344,
        "end": 851.065,
        "text": "You would have been better stuffing your money under a mattress.",
        "speaker": "SPEAKER_18"
    },
    {
        "start": 852.13,
        "end": 855.132,
        "text": " Yeah, this isn't hard math to figure out, even if you're a leftist.",
        "speaker": "SPEAKER_06"
    },
    {
        "start": 855.513,
        "end": 859.696,
        "text": "If inflation is, say, well, just, you know, pick fingers, 5%, five fingers, whatever.",
        "speaker": "SPEAKER_06"
    },
    {
        "start": 859.996,
        "end": 866.662,
        "text": "Inflation is 5%, and you make a 5% nominal gain in the stock market, you have not made any real money.",
        "speaker": "SPEAKER_06"
    },
    {
        "start": 867.122,
        "end": 871.866,
        "text": "So if you're then taxed on this fake gain, you have effectively lost money.",
        "speaker": "SPEAKER_06"
    },
    {
        "start": 872.046,
        "end": 881.834,
        "text": "In other words, what you could have bought before your fake 5% gain, you could actually buy less now because you've had to give that fake gain over to the government, which",
        "speaker": "SPEAKER_06"
    },
    {
        "start": 881.834,
        "end": 883.462,
        "text": " Which they then really take.",
        "speaker": "SPEAKER_06"
    },
    {
        "start": 885.158,
        "end": 885.939,
        "text": " Exactly, Dan.",
        "speaker": "SPEAKER_18"
    },
    {
        "start": 885.979,
        "end": 894.003,
        "text": "And this is the exact same thing that we see when this administration talks about how families are making more today than they ever have before.",
        "speaker": "SPEAKER_18"
    },
    {
        "start": 894.223,
        "end": 909.011,
        "text": "I mean, sure, that's true in a technical sense, but it's not really true in any meaningful sense because although the typical American family's weekly paycheck has gotten much bigger over the last couple of years, on average, it buys much less.",
        "speaker": "SPEAKER_18"
    },
    {
        "start": 909.131,
        "end": 909.792,
        "text": "How much less?",
        "speaker": "SPEAKER_18"
    },
    {
        "start": 909.852,
        "end": 910.372,
        "text": "About $4,000 less.",
        "speaker": "SPEAKER_18"
    },
    {
        "start": 912.453,
        "end": 914.896,
        "text": " Can you imagine what that does to families right now?",
        "speaker": "SPEAKER_18"
    },
    {
        "start": 915.156,
        "end": 919.02,
        "text": "You have countless Americans who can't even afford groceries.",
        "speaker": "SPEAKER_18"
    },
    {
        "start": 919.06,
        "end": 920.661,
        "text": "They're having to use credit cards.",
        "speaker": "SPEAKER_18"
    },
    {
        "start": 920.982,
        "end": 922.503,
        "text": "You know, Dan, I just saw a statistic.",
        "speaker": "SPEAKER_18"
    },
    {
        "start": 922.623,
        "end": 927.188,
        "text": "Half of American families right now can't afford back-to-school supplies for their kids.",
        "speaker": "SPEAKER_18"
    },
    {
        "start": 927.428,
        "end": 929.77,
        "text": "They can't even afford crayons and notebooks.",
        "speaker": "SPEAKER_18"
    },
    {
        "start": 929.85,
        "end": 930.771,
        "text": "This is insane.",
        "speaker": "SPEAKER_18"
    },
    {
        "start": 931.071,
        "end": 934.695,
        "text": "They're literally having to put this stuff on a credit card that they can't pay off.",
        "speaker": "SPEAKER_18"
    },
    {
        "start": 936.312,
        "end": 936.993,
        "text": " We're talking E.J.",
        "speaker": "SPEAKER_06"
    },
    {
        "start": 937.053,
        "end": 939.715,
        "text": "and Tony, economists over at Heritage.",
        "speaker": "SPEAKER_06"
    },
    {
        "start": 940.096,
        "end": 941.037,
        "text": "You're still at Heritage, right?",
        "speaker": "SPEAKER_06"
    },
    {
        "start": 941.157,
        "end": 941.677,
        "text": "Sorry, should I?",
        "speaker": "SPEAKER_06"
    },
    {
        "start": 941.697,
        "end": 943.719,
        "text": "You're still over there?",
        "speaker": "SPEAKER_06"
    },
    {
        "start": 943.919,
        "end": 944.8,
        "text": "I am, for now.",
        "speaker": "SPEAKER_18"
    },
    {
        "start": 944.82,
        "end": 945.26,
        "text": "We'll see.",
        "speaker": "SPEAKER_18"
    },
    {
        "start": 945.34,
        "end": 946.842,
        "text": "I don't know.",
        "speaker": "SPEAKER_18"
    },
    {
        "start": 947.062,
        "end": 947.462,
        "text": "Okay, good.",
        "speaker": "SPEAKER_06"
    },
    {
        "start": 947.522,
        "end": 948.363,
        "text": "I just want to check.",
        "speaker": "SPEAKER_06"
    },
    {
        "start": 948.704,
        "end": 949.584,
        "text": "But I hope they do.",
        "speaker": "SPEAKER_18"
    },
    {
        "start": 950.505,
        "end": 953.648,
        "text": "Well, we love you, and I follow you on social because you're always ahead of this stuff.",
        "speaker": "SPEAKER_06"
    },
    {
        "start": 953.848,
        "end": 958.713,
        "text": "You just said something I wanted to kind of reiterate to my audience as to why I believe politically.",
        "speaker": "SPEAKER_06"
    },
    {
        "start": 959.827,
        "end": 965.631,
        "text": " The economic ramifications of the Biden years have been far worse politically than they were in Obama.",
        "speaker": "SPEAKER_06"
    },
    {
        "start": 965.711,
        "end": 972.736,
        "text": "Obama managed to get reelected despite an economy, E.J., that you and I followed that candidly was probably just as bad.",
        "speaker": "SPEAKER_06"
    },
    {
        "start": 973.837,
        "end": 978.981,
        "text": "Obama in eight years never reached 3% GDP growth, the first president in modern history not to be able to do it.",
        "speaker": "SPEAKER_06"
    },
    {
        "start": 979.441,
        "end": 980.922,
        "text": " Productivity was in the tank.",
        "speaker": "SPEAKER_06"
    },
    {
        "start": 981.283,
        "end": 982.904,
        "text": "It was really a terrible economy.",
        "speaker": "SPEAKER_06"
    },
    {
        "start": 983.324,
        "end": 987.727,
        "text": "But Obama managed to get reelected because it was a couple of layers removed.",
        "speaker": "SPEAKER_06"
    },
    {
        "start": 988.068,
        "end": 994.292,
        "text": "He managed to distance himself from it by blaming greedy corporations and others.",
        "speaker": "SPEAKER_06"
    },
    {
        "start": 995.213,
        "end": 1003.7,
        "text": "The problem Biden has is inflation is a very unique economic crisis because everybody understands it just by...",
        "speaker": "SPEAKER_06"
    },
    {
        "start": 1004.46,
        "end": 1005.74,
        "text": " It's by the cash register.",
        "speaker": "SPEAKER_06"
    },
    {
        "start": 1005.78,
        "end": 1006.8,
        "text": "I mean, you can't hide it.",
        "speaker": "SPEAKER_06"
    },
    {
        "start": 1006.84,
        "end": 1015.062,
        "text": "You can't just go, oh, my gosh, look, you know, we hiked to corporate tax and those greedy corporations instead of reinvesting the money, blah, blah, blah, and talk people into a dish.",
        "speaker": "SPEAKER_06"
    },
    {
        "start": 1015.422,
        "end": 1017.082,
        "text": "They experience it every day.",
        "speaker": "SPEAKER_06"
    },
    {
        "start": 1017.562,
        "end": 1021.923,
        "text": "They may get a raise at work, but they realize, wow, I can't afford my insurance bill anymore.",
        "speaker": "SPEAKER_06"
    },
    {
        "start": 1021.943,
        "end": 1023.383,
        "text": "I can't afford my car payment.",
        "speaker": "SPEAKER_06"
    },
    {
        "start": 1023.743,
        "end": 1030.245,
        "text": "Inflation is a unique crisis that Biden created through this milieu of really horrible decision making.",
        "speaker": "SPEAKER_06"
    },
    {
        "start": 1030.605,
        "end": 1031.925,
        "text": "And that's why people get it.",
        "speaker": "SPEAKER_06"
    },
    {
        "start": 1032.305,
        "end": 1038.008,
        "text": " And I think that's why they're going to have a real problem pulling the lever for him if they're not diehard Democrats in this election.",
        "speaker": "SPEAKER_06"
    },
    {
        "start": 1039.509,
        "end": 1044.011,
        "text": "Well, Dan, and I think it's important to emphasize that this is not simply a Biden problem.",
        "speaker": "SPEAKER_18"
    },
    {
        "start": 1044.051,
        "end": 1046.332,
        "text": "This is a Biden-Harris problem.",
        "speaker": "SPEAKER_18"
    },
    {
        "start": 1046.672,
        "end": 1048.073,
        "text": "She owns this agenda.",
        "speaker": "SPEAKER_18"
    },
    {
        "start": 1048.113,
        "end": 1061.459,
        "text": "You know, not only was she the biggest cheerleader for all the runaway spending over the last several years as the vice president of this administration, but also as the president of the Senate, she cast two tie-breaking votes against",
        "speaker": "SPEAKER_18"
    },
    {
        "start": 1061.619,
        "end": 1066.942,
        "text": " for two of the three biggest spending bills we have seen over the last three and a half years.",
        "speaker": "SPEAKER_18"
    },
    {
        "start": 1067.242,
        "end": 1070.624,
        "text": "So she bears a tremendous amount of responsibility here.",
        "speaker": "SPEAKER_18"
    },
    {
        "start": 1070.884,
        "end": 1074.827,
        "text": "She has to own the inflation crisis because she helped cause it.",
        "speaker": "SPEAKER_18"
    },
    {
        "start": 1075.087,
        "end": 1087.354,
        "text": "And one other thing that we really need to point out, that these inflation numbers don't really capture the true cost of living crisis that families are facing today because they ignore regulatory costs.",
        "speaker": "SPEAKER_18"
    },
    {
        "start": 1088.054,
        "end": 1092.717,
        "text": " The Trump administration, I don't think, gets enough credit here for what they did with regulatory reform.",
        "speaker": "SPEAKER_18"
    },
    {
        "start": 1093.038,
        "end": 1100.963,
        "text": "They reduced regulatory costs on the average family by $2,000 per year every year through their efforts.",
        "speaker": "SPEAKER_18"
    },
    {
        "start": 1101.043,
        "end": 1105.506,
        "text": "Conversely, what has happened under the Biden-Harris administration, we've seen the opposite.",
        "speaker": "SPEAKER_18"
    },
    {
        "start": 1105.706,
        "end": 1112.17,
        "text": "We've seen regulatory burdens increase by $5,000 per family per year every year.",
        "speaker": "SPEAKER_18"
    },
    {
        "start": 1112.411,
        "end": 1117.374,
        "text": "That's a tremendous additional burden that isn't even counted in these inflation metrics.",
        "speaker": "SPEAKER_18"
    },
    {
        "start": 1118.374,
        "end": 1120.935,
        "text": " I think that's important that we all understand that, folks.",
        "speaker": "SPEAKER_06"
    },
    {
        "start": 1120.955,
        "end": 1121.496,
        "text": "What E.J.",
        "speaker": "SPEAKER_06"
    },
    {
        "start": 1121.516,
        "end": 1125.697,
        "text": "just said, government regulations are effectively attacked.",
        "speaker": "SPEAKER_06"
    },
    {
        "start": 1125.737,
        "end": 1126.938,
        "text": "I'll just give you a quick example.",
        "speaker": "SPEAKER_06"
    },
    {
        "start": 1127.178,
        "end": 1129.339,
        "text": "I have this Secret Service coin on my desk or whatever.",
        "speaker": "SPEAKER_06"
    },
    {
        "start": 1129.359,
        "end": 1130.119,
        "text": "It looks like an old badge.",
        "speaker": "SPEAKER_06"
    },
    {
        "start": 1130.139,
        "end": 1139.403,
        "text": "Let's say you work for one of these coin makers and Biden puts out a regulation saying, if you make a coin with this type of metal, you're going to have to pay for an environmental analysis.",
        "speaker": "SPEAKER_06"
    },
    {
        "start": 1139.783,
        "end": 1143.665,
        "text": "The environmental analysis could cost ten, fifteen thousand dollars.",
        "speaker": "SPEAKER_06"
    },
    {
        "start": 1144.125,
        "end": 1149.547,
        "text": " Candidly, EJ, I'd rather pay a tax that cost me $2,000 than a regulation that cost me $10,000.",
        "speaker": "SPEAKER_06"
    },
    {
        "start": 1149.908,
        "end": 1164.234,
        "text": "So when you talk about things like Trump's deregulation and his destruction of government red tape, which is a matter of record, you can go look at the Federal Register, compared to Biden growing the Federal Register and just dramatically expanding red tape, these aren't...",
        "speaker": "SPEAKER_06"
    },
    {
        "start": 1164.734,
        "end": 1166.418,
        "text": " secondary tertiary costs.",
        "speaker": "SPEAKER_06"
    },
    {
        "start": 1166.658,
        "end": 1174.793,
        "text": "This is real money coming out of your business's wallet and bank account that is then not going to workers to create cheaper products.",
        "speaker": "SPEAKER_06"
    },
    {
        "start": 1176.233,
        "end": 1177.094,
        "text": " Exactly, Dan.",
        "speaker": "SPEAKER_18"
    },
    {
        "start": 1177.134,
        "end": 1178.154,
        "text": "You're spot on here.",
        "speaker": "SPEAKER_18"
    },
    {
        "start": 1178.655,
        "end": 1185.459,
        "text": "And again, we've got to emphasize that when you hear in the news, oh, inflation is down, everything's fine.",
        "speaker": "SPEAKER_18"
    },
    {
        "start": 1185.8,
        "end": 1186.12,
        "text": "Really?",
        "speaker": "SPEAKER_18"
    },
    {
        "start": 1186.18,
        "end": 1191.523,
        "text": "Then why do I keep paying more when I fill up my tank or when I put groceries in the backseat?",
        "speaker": "SPEAKER_18"
    },
    {
        "start": 1191.784,
        "end": 1195.406,
        "text": "Why is it I'm driving around on bald tires because I can't afford new ones?",
        "speaker": "SPEAKER_18"
    },
    {
        "start": 1195.726,
        "end": 1199.229,
        "text": "Why are these costs still going up when they tell me inflation is down?",
        "speaker": "SPEAKER_18"
    },
    {
        "start": 1199.609,
        "end": 1203.712,
        "text": "A lot of that has to do with the fact that they're not counting many of these costs.",
        "speaker": "SPEAKER_18"
    },
    {
        "start": 1207.053,
        "end": 1207.774,
        "text": " Yeah, they're real.",
        "speaker": "SPEAKER_06"
    },
    {
        "start": 1208.134,
        "end": 1218.797,
        "text": "E.J., one more Biden-era initiative, which, again, no sane person can question unless you're a hyper-partisan gaslighting lunatic, is the Biden team has not been friendly to a pro-energy agenda.",
        "speaker": "SPEAKER_06"
    },
    {
        "start": 1219.057,
        "end": 1219.817,
        "text": "They just haven't.",
        "speaker": "SPEAKER_06"
    },
    {
        "start": 1220.117,
        "end": 1232.601,
        "text": "Between LNG export restrictions, refinery restrictions, pipeline permitting issues, you know, even Joe Manchin, who's a Democrat, a phony whatever, but even Manchin tried to push for a permitting restriction relief.",
        "speaker": "SPEAKER_06"
    },
    {
        "start": 1232.961,
        "end": 1235.023,
        "text": " Because if you're not going to have pipelines, you're not going to have gases.",
        "speaker": "SPEAKER_06"
    },
    {
        "start": 1235.043,
        "end": 1236.064,
        "text": "What are you going to do?",
        "speaker": "SPEAKER_06"
    },
    {
        "start": 1236.104,
        "end": 1237.365,
        "text": "Transport it by rail?",
        "speaker": "SPEAKER_06"
    },
    {
        "start": 1237.485,
        "end": 1238.246,
        "text": "It's dangerous.",
        "speaker": "SPEAKER_06"
    },
    {
        "start": 1238.306,
        "end": 1239.127,
        "text": "It's laborious.",
        "speaker": "SPEAKER_06"
    },
    {
        "start": 1239.447,
        "end": 1240.047,
        "text": "It doesn't work.",
        "speaker": "SPEAKER_06"
    },
    {
        "start": 1240.648,
        "end": 1241.328,
        "text": "They've done this.",
        "speaker": "SPEAKER_06"
    },
    {
        "start": 1241.729,
        "end": 1245.052,
        "text": "Energy is fed into every price of everything.",
        "speaker": "SPEAKER_06"
    },
    {
        "start": 1245.072,
        "end": 1252.238,
        "text": "There's nothing out there made besides maybe you, John J. Rambo style, whittling away at a piece of wood to make a spike out of it.",
        "speaker": "SPEAKER_06"
    },
    {
        "start": 1252.618,
        "end": 1256.922,
        "text": "Everything's going to require some form of energy, petrochemicals, everything.",
        "speaker": "SPEAKER_06"
    },
    {
        "start": 1257.543,
        "end": 1259.905,
        "text": "Not to mention the plastics that come out of it and everything else.",
        "speaker": "SPEAKER_06"
    },
    {
        "start": 1260.345,
        "end": 1266.351,
        "text": " There has not been a more anti-energy agenda team than Kamala Harris and Joe Biden.",
        "speaker": "SPEAKER_06"
    },
    {
        "start": 1266.672,
        "end": 1273.178,
        "text": "And that's another imposed tax on America as their heating bills go up, their gas bills go up.",
        "speaker": "SPEAKER_06"
    },
    {
        "start": 1273.439,
        "end": 1279.305,
        "text": "This is a de facto tax, if not a de jure one, right out of the chute that's costing people real money.",
        "speaker": "SPEAKER_06"
    },
    {
        "start": 1280.931,
        "end": 1283.013,
        "text": " Dan, you are spot on again here, 100%.",
        "speaker": "SPEAKER_18"
    },
    {
        "start": 1284.334,
        "end": 1296.283,
        "text": "Look, not only does energy affect the price of everything we do and everything we buy, but in America, because we can get natural gas out of the ground so much cheaper than most of the rest of the world,",
        "speaker": "SPEAKER_18"
    },
    {
        "start": 1296.603,
        "end": 1301.146,
        "text": " We actually use that and not oil for a lot of our chemical blend stocks.",
        "speaker": "SPEAKER_18"
    },
    {
        "start": 1301.206,
        "end": 1312.772,
        "text": "In other words, we use natural gas to make everything from the polyester fibers in your clothing to the plastic in your cell phone to even components in your car engine and everything in between.",
        "speaker": "SPEAKER_18"
    },
    {
        "start": 1313.152,
        "end": 1315.173,
        "text": "And so what happens is when you raise...",
        "speaker": "SPEAKER_18"
    },
    {
        "start": 1315.553,
        "end": 1322.861,
        "text": " an input cost that is as ubiquitous as natural gas, you are going to cause costs to go up throughout the economy.",
        "speaker": "SPEAKER_18"
    },
    {
        "start": 1323.142,
        "end": 1326.586,
        "text": "And sure enough, that's what we've seen under this administration.",
        "speaker": "SPEAKER_18"
    },
    {
        "start": 1326.826,
        "end": 1331.331,
        "text": "These are the people that killed the Keystone XL pipeline literally on day one.",
        "speaker": "SPEAKER_18"
    },
    {
        "start": 1331.671,
        "end": 1336.417,
        "text": "From the beginning until all the way until today, they have been anti-energy.",
        "speaker": "SPEAKER_18"
    },
    {
        "start": 1337.463,
        "end": 1338.624,
        "text": " E.J., I know I said it was the last question.",
        "speaker": "SPEAKER_06"
    },
    {
        "start": 1338.704,
        "end": 1338.964,
        "text": "One more.",
        "speaker": "SPEAKER_06"
    },
    {
        "start": 1338.984,
        "end": 1340.405,
        "text": "I got two minutes left.",
        "speaker": "SPEAKER_06"
    },
    {
        "start": 1340.425,
        "end": 1343.607,
        "text": "There's a thing in economics you and I both know called the substitution effect.",
        "speaker": "SPEAKER_06"
    },
    {
        "start": 1343.628,
        "end": 1345.829,
        "text": "You know, price of chicken goes up, people buy more beef.",
        "speaker": "SPEAKER_06"
    },
    {
        "start": 1345.869,
        "end": 1347.27,
        "text": "Price of beef goes up, they buy pork.",
        "speaker": "SPEAKER_06"
    },
    {
        "start": 1347.71,
        "end": 1348.671,
        "text": "You can substitute.",
        "speaker": "SPEAKER_06"
    },
    {
        "start": 1348.851,
        "end": 1350.773,
        "text": "You may not like it, but there's a way out of it.",
        "speaker": "SPEAKER_06"
    },
    {
        "start": 1351.193,
        "end": 1353.655,
        "text": "That's not the case with energy prices.",
        "speaker": "SPEAKER_06"
    },
    {
        "start": 1353.975,
        "end": 1355.056,
        "text": "What you just said is accurate.",
        "speaker": "SPEAKER_06"
    },
    {
        "start": 1355.236,
        "end": 1364.002,
        "text": "There's no way to avoid energy prices if you're going to restrict energy like the Biden administration with Harris are committed to.",
        "speaker": "SPEAKER_06"
    },
    {
        "start": 1364.022,
        "end": 1364.743,
        "text": "There's just no way.",
        "speaker": "SPEAKER_06"
    },
    {
        "start": 1364.803,
        "end": 1366.244,
        "text": "It's built into every single thing.",
        "speaker": "SPEAKER_06"
    },
    {
        "start": 1367.859,
        "end": 1368.639,
        "text": " That's right, Dan.",
        "speaker": "SPEAKER_18"
    },
    {
        "start": 1368.779,
        "end": 1374.702,
        "text": "And that substitution effect, by the way, that happens not only at the local level, right?",
        "speaker": "SPEAKER_18"
    },
    {
        "start": 1374.742,
        "end": 1379.864,
        "text": "It happens not only when the individual consumer is choosing, like you mentioned, what kind of meat do I want to buy?",
        "speaker": "SPEAKER_18"
    },
    {
        "start": 1380.124,
        "end": 1382.445,
        "text": "It happens at the international level as well.",
        "speaker": "SPEAKER_18"
    },
    {
        "start": 1382.745,
        "end": 1390.528,
        "text": "In other words, when we're not producing enough energy exports, countries have to turn to sometimes hostile nations like Iran.",
        "speaker": "SPEAKER_18"
    },
    {
        "start": 1390.548,
        "end": 1390.688,
        "text": "Right.",
        "speaker": "SPEAKER_18"
    },
    {
        "start": 1390.928,
        "end": 1392.231,
        "text": " and buy energy for them.",
        "speaker": "SPEAKER_18"
    },
    {
        "start": 1392.251,
        "end": 1400.707,
        "text": "And so now, instead of money going to put Americans to work, you're putting money into the coffers of the warlords in Iran, and you're funding terrorism.",
        "speaker": "SPEAKER_18"
    },
    {
        "start": 1401.556,
        "end": 1401.796,
        "text": " Right.",
        "speaker": "SPEAKER_06"
    },
    {
        "start": 1401.956,
        "end": 1406.2,
        "text": "And it's just amazing how we're funding this war in Ukraine.",
        "speaker": "SPEAKER_06"
    },
    {
        "start": 1406.22,
        "end": 1408.181,
        "text": "Whatever your position is, I'm not even going to talk about that now.",
        "speaker": "SPEAKER_06"
    },
    {
        "start": 1408.442,
        "end": 1409.142,
        "text": "It's for another day.",
        "speaker": "SPEAKER_06"
    },
    {
        "start": 1409.903,
        "end": 1417.809,
        "text": "But we're funding a war in Ukraine while simultaneously restricting our own natural gas supply to allow others to buy natural gas to Russia.",
        "speaker": "SPEAKER_06"
    },
    {
        "start": 1418.289,
        "end": 1422.433,
        "text": "We're like effectively funding both sides of this war, which is an obscenity.",
        "speaker": "SPEAKER_06"
    },
    {
        "start": 1422.913,
        "end": 1423.894,
        "text": " E.J., you're awesome.",
        "speaker": "SPEAKER_06"
    },
    {
        "start": 1423.914,
        "end": 1425.335,
        "text": "I need to follow you.",
        "speaker": "SPEAKER_06"
    },
    {
        "start": 1425.355,
        "end": 1425.836,
        "text": "E.J.",
        "speaker": "SPEAKER_06"
    },
    {
        "start": 1425.916,
        "end": 1429.179,
        "text": "Antoni, he is on social media, on X and elsewhere.",
        "speaker": "SPEAKER_06"
    },
    {
        "start": 1429.219,
        "end": 1433.723,
        "text": "Give him a follow if you want to stay way ahead of the curve on the economics news of the day.",
        "speaker": "SPEAKER_06"
    },
    {
        "start": 1434.144,
        "end": 1435.805,
        "text": "E.J., we'll have you back as always.",
        "speaker": "SPEAKER_06"
    },
    {
        "start": 1435.865,
        "end": 1437.827,
        "text": "You're our resident economist on the show.",
        "speaker": "SPEAKER_06"
    },
    {
        "start": 1437.867,
        "end": 1438.228,
        "text": "We love you.",
        "speaker": "SPEAKER_06"
    },
    {
        "start": 1438.248,
        "end": 1439.048,
        "text": "Thanks for coming on today.",
        "speaker": "SPEAKER_06"
    },
    {
        "start": 1439.088,
        "end": 1440.65,
        "text": "Appreciate it.",
        "speaker": "SPEAKER_06"
    },
    {
        "start": 1440.69,
        "end": 1441.511,
        "text": "My pleasure, Dan.",
        "speaker": "SPEAKER_18"
    },
    {
        "start": 1441.531,
        "end": 1442.612,
        "text": "Thank you for having me.",
        "speaker": "SPEAKER_18"
    },
    {
        "start": 1443.297,
        "end": 1443.777,
        "text": " You got it.",
        "speaker": "SPEAKER_06"
    },
    {
        "start": 1443.797,
        "end": 1444.998,
        "text": "That guy's one of the best folks.",
        "speaker": "SPEAKER_06"
    },
    {
        "start": 1445.038,
        "end": 1446.459,
        "text": "Please give him a follow on social media.",
        "speaker": "SPEAKER_06"
    },
    {
        "start": 1446.559,
        "end": 1448.701,
        "text": "EJ and Tony, it's worth your time.",
        "speaker": "SPEAKER_06"
    },
    {
        "start": 1449.201,
        "end": 1452.243,
        "text": "Look about look at all the numbers he has up there on consumer debt.",
        "speaker": "SPEAKER_06"
    },
    {
        "start": 1452.283,
        "end": 1453.644,
        "text": "The economy is worse than you think.",
        "speaker": "SPEAKER_06"
    },
    {
        "start": 1453.884,
        "end": 1455.145,
        "text": "You know, I haven't been dramatic.",
        "speaker": "SPEAKER_06"
    },
    {
        "start": 1455.465,
        "end": 1456.926,
        "text": "It's not the worst we've ever seen.",
        "speaker": "SPEAKER_06"
    },
    {
        "start": 1457.266,
        "end": 1459.728,
        "text": "I'm never going to engage in hyperbole to spin your wheels.",
        "speaker": "SPEAKER_06"
    },
    {
        "start": 1460.208,
        "end": 1461.269,
        "text": "OK, I'm not going to do that.",
        "speaker": "SPEAKER_06"
    },
    {
        "start": 1462.549,
        "end": 1464.711,
        "text": "It's bad enough that we should vote the right way.",
        "speaker": "SPEAKER_06"
    },
    {
        "start": 1465.762,
        "end": 1474.313,
        "text": " I'm just telling you, it's not as bad as some people will tell you, but it's a lot worse than Biden and Harris are telling you and the media.",
        "speaker": "SPEAKER_06"
    },
    {
        "start": 1475.234,
        "end": 1478.098,
        "text": "You look at the numbers and you'll see exactly what I'm talking about.",
        "speaker": "SPEAKER_06"
    },
    {
        "start": 1478.298,
        "end": 1480.1,
        "text": "Real wages, consumer debt.",
        "speaker": "SPEAKER_06"
    },
    {
        "start": 1480.601,
        "end": 1481.722,
        "text": "We are in a lot of trouble.",
        "speaker": "SPEAKER_06"
    },
    {
        "start": 1482.743,
        "end": 1483.344,
        "text": "More coming up next.",
        "speaker": "SPEAKER_06"
    },
    {
        "start": 1483.384,
        "end": 1483.905,
        "text": "We'll be right back.",
        "speaker": "SPEAKER_06"
    },
    {
        "start": 1488.877,
        "end": 1497.342,
        "text": " Celebrate more than 100 years of America's original butcher and save 50% off site-wide during the Omaha Steaks anniversary sale.",
        "speaker": "SPEAKER_14"
    },
    {
        "start": 1497.482,
        "end": 1508.189,
        "text": "That's right, Omaha Steaks is delivering unforgettable flavor with 50% off extra-aged grain-finished steaks, juicy pure-ground burgers, premium pork, air-chilled chicken, and so much more.",
        "speaker": "SPEAKER_14"
    },
    {
        "start": 1508.209,
        "end": 1516.234,
        "text": "Plus, as a special offer, you'll get an extra $30 off your order when you shop today at omahasteaks.com and use promo code SIZZLE at checkout.",
        "speaker": "SPEAKER_14"
    },
    {
        "start": 1516.414,
        "end": 1524.378,
        "text": " For five generations, Omaha Steaks has brought you endless flavor, endless variety, and endless value with premium proteins that are sure to satisfy.",
        "speaker": "SPEAKER_14"
    },
    {
        "start": 1524.558,
        "end": 1526.439,
        "text": "And right now, they're all 50% off.",
        "speaker": "SPEAKER_14"
    },
    {
        "start": 1526.96,
        "end": 1531.802,
        "text": "Plus, don't forget, when you use promo code sizzle at checkout, get the extra $30 off.",
        "speaker": "SPEAKER_14"
    },
    {
        "start": 1531.962,
        "end": 1536.544,
        "text": "Shop for anniversary savings on all the legendary flavors from America's original butcher.",
        "speaker": "SPEAKER_14"
    },
    {
        "start": 1536.665,
        "end": 1538.345,
        "text": "But hurry, this offer won't last long.",
        "speaker": "SPEAKER_14"
    },
    {
        "start": 1538.526,
        "end": 1540.166,
        "text": "That's omahasteaks.com.",
        "speaker": "SPEAKER_14"
    },
    {
        "start": 1540.226,
        "end": 1541.987,
        "text": "Promo code sizzle at checkout.",
        "speaker": "SPEAKER_14"
    },
    {
        "start": 1542.087,
        "end": 1542.948,
        "text": "Minimum purchase may apply.",
        "speaker": "SPEAKER_14"
    },
    {
        "start": 1544.233,
        "end": 1547.138,
        "text": " Omaha Steaks, America's original butcher.",
        "speaker": "SPEAKER_16"
    },
    {
        "start": 1550.123,
        "end": 1551.786,
        "text": "Dan Bongino.",
        "speaker": "SPEAKER_13"
    },
    {
        "start": 1552.427,
        "end": 1552.707,
        "text": "WISL.",
        "speaker": "SPEAKER_09"
    },
    {
        "start": 1563.604,
        "end": 1568.447,
        "text": " Summer adventures, savings, and selection are yours when you shop Victor's Chevrolet.",
        "speaker": "SPEAKER_17"
    },
    {
        "start": 1568.507,
        "end": 1574.09,
        "text": "Lease a 2024 Chevy Trailblazer LT for just $199 a month for 27 months.",
        "speaker": "SPEAKER_17"
    },
    {
        "start": 1574.11,
        "end": 1579.913,
        "text": "If you need a pickup, get the versatility of a 2024 Chevy Silverado LT crew cab.",
        "speaker": "SPEAKER_17"
    },
    {
        "start": 1580.113,
        "end": 1582.914,
        "text": "Just $339 a month for 27 months.",
        "speaker": "SPEAKER_17"
    },
    {
        "start": 1583.035,
        "end": 1585.376,
        "text": "A 24 Chevy Equinox all-wheel drive LT.",
        "speaker": "SPEAKER_17"
    },
    {
        "start": 1585.896,
        "end": 1588.058,
        "text": " Only $249 a month for 27 months.",
        "speaker": "SPEAKER_17"
    },
    {
        "start": 1588.419,
        "end": 1590.621,
        "text": "$2,500 cash or trade equity closing with all leases.",
        "speaker": "SPEAKER_17"
    },
    {
        "start": 1590.801,
        "end": 1593.063,
        "text": "All factoring rebates, incentives, and discounts are applied.",
        "speaker": "SPEAKER_17"
    },
    {
        "start": 1593.103,
        "end": 1594.285,
        "text": "Security deposit is waived.",
        "speaker": "SPEAKER_17"
    },
    {
        "start": 1594.385,
        "end": 1595.886,
        "text": "Includes returning lessee rebate.",
        "speaker": "SPEAKER_17"
    },
    {
        "start": 1596.166,
        "end": 1597.107,
        "text": "10,000 mile allowance per year.",
        "speaker": "SPEAKER_17"
    },
    {
        "start": 1597.127,
        "end": 1598.629,
        "text": "25 cents each additional mile.",
        "speaker": "SPEAKER_17"
    },
    {
        "start": 1598.729,
        "end": 1599.79,
        "text": "Must have lease and household.",
        "speaker": "SPEAKER_17"
    },
    {
        "start": 1599.93,
        "end": 1601.332,
        "text": "Tier 1 credit approval required.",
        "speaker": "SPEAKER_17"
    },
    {
        "start": 1601.432,
        "end": 1603.173,
        "text": "Lessee responsible for repair and maintenance.",
        "speaker": "SPEAKER_17"
    },
    {
        "start": 1603.193,
        "end": 1603.854,
        "text": "Conditions apply.",
        "speaker": "SPEAKER_17"
    },
    {
        "start": 1603.914,
        "end": 1604.735,
        "text": "Get details at dealer.",
        "speaker": "SPEAKER_17"
    },
    {
        "start": 1604.755,
        "end": 1607.717,
        "text": " Victor Chevrolet has an unbeatable use selection, too.",
        "speaker": "SPEAKER_17"
    },
    {
        "start": 1607.797,
        "end": 1612.179,
        "text": "Whatever the make, trust your vehicle to our Chevy Certified Service Department.",
        "speaker": "SPEAKER_17"
    },
    {
        "start": 1612.239,
        "end": 1615.14,
        "text": "Come see how easy it is to do business with us.",
        "speaker": "SPEAKER_17"
    },
    {
        "start": 1615.601,
        "end": 1619.983,
        "text": "Together, let's drive at Victor Chevrolet Route 96 in Victor.",
        "speaker": "SPEAKER_17"
    },
    {
        "start": 1620.043,
        "end": 1621.844,
        "text": "Visit VictorChevrolet.com.",
        "speaker": "SPEAKER_17"
    },
    {
        "start": 1624.733,
        "end": 1628.936,
        "text": " Live harness racing has returned to Batavia Downs for the summer of 2024.",
        "speaker": "SPEAKER_08"
    },
    {
        "start": 1629.397,
        "end": 1632.239,
        "text": "Sponsored by Roswell Park Comprehensive Cancer Center.",
        "speaker": "SPEAKER_08"
    },
    {
        "start": 1632.659,
        "end": 1636.603,
        "text": "Join us inside our clubhouse or watch the great harness racing trackside.",
        "speaker": "SPEAKER_08"
    },
    {
        "start": 1636.903,
        "end": 1639.485,
        "text": "Make a night of it by staying in our beautiful hotel.",
        "speaker": "SPEAKER_08"
    },
    {
        "start": 1639.725,
        "end": 1646.31,
        "text": "Plan your summer fun by checking out the full schedule at all of our events and hotel deals on BataviaDownsGaming.com.",
        "speaker": "SPEAKER_08"
    },
    {
        "start": 1646.691,
        "end": 1649.393,
        "text": "Dine, play, and stay at Batavia Downs.",
        "speaker": "SPEAKER_08"
    },
    {
        "start": 1652.418,
        "end": 1652.738,
        "text": " W-Y-S-L!",
        "speaker": "SPEAKER_24"
    },
    {
        "start": 1652.758,
        "end": 1676.942,
        "text": "T-W-O-R-L-D, T-Girl, T-Girl, Lingerie, that's rockin' the world, makin' things swirl, causin' a swirl, T-W-O-R-L-D, it go, you go, don't slip, you take shifts, satellites drift, tide rise up, trip, jump, drop, trip, time to switch, glaciers tip, barometer dips, sun low, solar eclipse, T-World Launch!",
        "speaker": "SPEAKER_24"
    },
    {
        "start": 1682.435,
        "end": 1689.68,
        "text": " Cobblestone Capital Advisors, LLC, offers comprehensive financial management services throughout western New York and nationwide.",
        "speaker": "SPEAKER_16"
    },
    {
        "start": 1689.88,
        "end": 1701.468,
        "text": "Cobblestone's an active supporter of numerous local organizations, including Mary Cariola Children's Center, Wilmot Cancer Center, Holy Childhood, Rochester Child First Network, and Golisano Children's Hospital.",
        "speaker": "SPEAKER_16"
    },
    {
        "start": 1701.628,
        "end": 1708.272,
        "text": "Since 1986, Cobblestone Capital Advisors has been building strong foundations for both its clients and its community.",
        "speaker": "SPEAKER_16"
    },
    {
        "start": 1708.392,
        "end": 1712.255,
        "text": "Cobblestone Capital Advisors, focused on one goal, yours.",
        "speaker": "SPEAKER_16"
    },
    {
        "start": 1713.216,
        "end": 1717.359,
        "text": " Are skyrocketing costs causing you to look at your budget and pinching your wallet?",
        "speaker": "SPEAKER_21"
    },
    {
        "start": 1717.659,
        "end": 1721.203,
        "text": "Your auto, home, and business insurance doesn't need to follow suit.",
        "speaker": "SPEAKER_21"
    },
    {
        "start": 1721.563,
        "end": 1726.287,
        "text": "Get a fair and honest rate comparison with a knowledgeable staff at the Long Agency.",
        "speaker": "SPEAKER_21"
    },
    {
        "start": 1726.687,
        "end": 1728.249,
        "text": "Your local insurance agent.",
        "speaker": "SPEAKER_21"
    },
    {
        "start": 1728.529,
        "end": 1734.514,
        "text": "Contact us at 585-658-3342 or longagency.com.",
        "speaker": "SPEAKER_21"
    },
    {
        "start": 1734.734,
        "end": 1736.716,
        "text": "Proudly representing Erie Insurance.",
        "speaker": "SPEAKER_21"
    },
    {
        "start": 1736.976,
        "end": 1737.797,
        "text": "Long Agency.",
        "speaker": "SPEAKER_21"
    },
    {
        "start": 1737.977,
        "end": 1739.058,
        "text": "Insurance worth having.",
        "speaker": "SPEAKER_21"
    },
    {
        "start": 1742.586,
        "end": 1747.432,
        "text": " W.Y.S.L.",
        "speaker": "SPEAKER_09"
    },
    {
        "start": 1751.436,
        "end": 1755.2,
        "text": "Four out of five Democrats secretly listen and learn something.",
        "speaker": "SPEAKER_13"
    },
    {
        "start": 1755.581,
        "end": 1756.922,
        "text": "The Dan Bongino Show.",
        "speaker": "SPEAKER_13"
    },
    {
        "start": 1758.45,
        "end": 1761.471,
        "text": " Folks, we do those economic segments on the show for a reason.",
        "speaker": "SPEAKER_06"
    },
    {
        "start": 1761.591,
        "end": 1763.192,
        "text": "You know, they call it the dismal science.",
        "speaker": "SPEAKER_06"
    },
    {
        "start": 1763.232,
        "end": 1763.652,
        "text": "I get that.",
        "speaker": "SPEAKER_06"
    },
    {
        "start": 1763.672,
        "end": 1765.233,
        "text": "I'm never going to spin your wheels on the show.",
        "speaker": "SPEAKER_06"
    },
    {
        "start": 1766.113,
        "end": 1771.415,
        "text": "Economics is not, if framed the wrong way, it could be one of the most boring subjects you'll ever take.",
        "speaker": "SPEAKER_06"
    },
    {
        "start": 1771.475,
        "end": 1773.476,
        "text": "If framed the right way, it explains everything.",
        "speaker": "SPEAKER_06"
    },
    {
        "start": 1774.156,
        "end": 1779.318,
        "text": "And the thing I love about economics and why we do those segments about twice a month, that interview with E.J.",
        "speaker": "SPEAKER_06"
    },
    {
        "start": 1779.378,
        "end": 1780.498,
        "text": "and Tony was fantastic.",
        "speaker": "SPEAKER_06"
    },
    {
        "start": 1780.518,
        "end": 1782.019,
        "text": "We're going to put it on the weekend interview show.",
        "speaker": "SPEAKER_06"
    },
    {
        "start": 1782.039,
        "end": 1783.62,
        "text": "A couple people already requested it.",
        "speaker": "SPEAKER_06"
    },
    {
        "start": 1784.0,
        "end": 1786.941,
        "text": "Explains everything as to why the economy is in the malaise it's in right now.",
        "speaker": "SPEAKER_06"
    },
    {
        "start": 1789.09,
        "end": 1792.713,
        "text": " The reason I do that is I promise you, I give you my word as your friend.",
        "speaker": "SPEAKER_06"
    },
    {
        "start": 1793.513,
        "end": 1809.065,
        "text": "Once you understand even basic economics, I'm not talking about advanced level Keynesian propensity to save stuff, just basic economics, simple supply demand, how margins work and things like that, and opportunity costs, simple stuff you can learn in a day.",
        "speaker": "SPEAKER_06"
    },
    {
        "start": 1809.826,
        "end": 1812.748,
        "text": "I mean that in the literal sense, in a day, in a couple hour course.",
        "speaker": "SPEAKER_06"
    },
    {
        "start": 1814.229,
        "end": 1815.851,
        "text": "You can't unsee it, ever.",
        "speaker": "SPEAKER_06"
    },
    {
        "start": 1816.311,
        "end": 1816.391,
        "text": "You",
        "speaker": "SPEAKER_06"
    }
]